[
  {
    "id": "ann_001",
    "title": "مهرجان القراءة السنوي",
    "description": "انطلاق فعاليات مهرجان القراءة مع إصدارات جديدة وبرامج متنوعة مع احدث التفاصيل الصغيرة المهخمة التي يتضح فيها اهم الامور التي تخص المكتية واحدث اصداراتها .",
    "imageUrl": "https://raw.githubusercontent.com/hh047871-pixel/electronic-library-data/main/banners/4.jpg",
    "type": "حدث",
    "link": "https://example.com/event-001",
    "createdAt": "2026-02-22T11:00:00+03:00",
    "startAt": "2026-02-24T12:00:00+03:00",
    "endAt": "2026-02-25T12:01:00+03:00",
    "isActive": true
  },
  {
    "id": "ann_002",
    "title": "إطلاق قسم جديد في المكتبة للكتب",
    "description": "تمت إضافة مجموعة كتب جديدة ضمن أقسام المكتبة الإلكترونية.",
    "imageUrl": "https://raw.githubusercontent.com/hh047871-pixel/electronic-library-data/main/banners/4.jpg",
    "type": "حدث",
    "link": "https://example.com/event-002",
    "createdAt": "2026-02-20T15:30:00+03:00",
    "startAt": "2026-02-20T15:30:00+03:00",
    "endAt": "2026-02-21T23:00:00+03:00",
    "isActive": true
  },
  {
    "id": "ann_003",
    "title": "أسبوع الكتاب الإسلامي",
    "description": "برنامج أسبوعي يتضمن عروضًا خاصة وتعريفًا بإصدارات مختارة يوميًا.",
    "imageUrl": "https://raw.githubusercontent.com/hh047871-pixel/electronic-library-data/main/banners/4.jpg",
    "type": "حدث",
    "link": "https://example.com/event-003",
    "createdAt": "2026-02-23T12:15:00+03:00",
    "startAt": "2026-02-25T13:00:00+03:00",
    "endAt": "2026-03-06T01:00:00+03:00",
    "isActive": true
  },
  {
    "id": "ann_004",
    "title": "فعالية توقيع الإصدارات الجديدة",
    "description": "متابعة خاصة لإطلاق الإصدارات الجديدة مع تغطية لأبرز العناوين المشاركة.",
    "imageUrl": "https://raw.githubusercontent.com/hh047871-pixel/electronic-library-data/main/banners/4.jpg",
    "type": "حدث",
    "link": "https://example.com/event-004",
    "createdAt": "2026-02-21T19:45:00+03:00",
    "startAt": "2026-02-26T19:45:00+03:00",
    "endAt": "2026-03-03T21:30:00+03:00",
    "isActive": true
  },
  {
    "id": "offer_001",
    "title": "عرض نهاية الأسبوع",
    "description": "خصم خاص على مجموعة من الكتب المختارة لفترة محدودة.",
    "imageUrl": "https://raw.githubusercontent.com/hh047871-pixel/electronic-library-data/main/banners/4.jpg",
    "type": "عرض",
    "link": "https://example.com/offer-001",
    "createdAt": "2026-02-22T13:00:00+03:00",
    "isActive": true
  },
  {
    "id": "offer_002",
    "title": "عرض الكتب المميزة",
    "description": "عروض خاصة على الكتب المميزة مع تحديثات مستمرة.",
    "imageUrl": "https://raw.githubusercontent.com/hh047871-pixel/electronic-library-data/main/banners/4.jpg",
    "type": "عرض",
    "link": "https://example.com/offer-002",
    "createdAt": "2026-02-21T17:20:00+03:00",
    "isActive": true
  }
]